text_numbers/__init__.py
text_numbers-0.1.0.dist-info/METADATA
text_numbers-0.1.0.dist-info/WHEEL
text_numbers-0.1.0.dist-info/entry_points.txt
text_numbers-0.1.0.dist-info/RECORD
