Metadata-Version: 2.1
Name: text-numbers
Version: 0.1.0
Summary: Convert words to numbers.
License: MIT
Author: Zachary Blackwood
Author-email: zblackwo@gmail.com
Requires-Python: >=3.7,<4.0
Classifier: License :: OSI Approved :: MIT License
Classifier: Programming Language :: Python :: 3
Classifier: Programming Language :: Python :: 3.7
Classifier: Programming Language :: Python :: 3.8
Classifier: Programming Language :: Python :: 3.9
Classifier: Programming Language :: Python :: 3.10
Classifier: Programming Language :: Python :: 3.11
Project-URL: repository, https://github.com/blackary/text-numbers
